{"crane_code" : "",
  "crane_name" : "",
  "job_type" : "",
  "is_locked" : true,
  "lock_time" : "",
  "user_name" : "",
  "start_time" : "",
  "end_time" : "",
  "truck_no" : "",
  "ocr_truck_no" : "",
  "total_weight" : "",
  "container_amount" : 0,
  "containers" : [
    {
      "position" : "前",
      "container_no" : "",
      "ocr_container_no" : "",
      "iso_code" : "",
      "job_type" : "",
      "vessel_position" : "",
      "yard_position" : "",
      "container_property" : "",
      "is_matched" : false,
      "damages" : []
    },
    {
      "position" : "后",
      "container_no" : "",
      "ocr_container_no" : "",
      "iso_code" : "",
      "job_type" : "",
      "vessel_position" : "",
      "yard_position" : "",
      "container_property" : "",
      "is_matched" : false,
      "damages" : []
    }
  ],
  "pictures" : [],
  "processes" : {},
  "update_time" : ""
}